abstractagents/__init__.py
abstractagents/py.typed
abstractagents-0.1.0.dist-info/licenses/LICENSE
abstractagents-0.1.0.dist-info/METADATA
abstractagents-0.1.0.dist-info/WHEEL
abstractagents-0.1.0.dist-info/top_level.txt
abstractagents-0.1.0.dist-info/RECORD
