Metadata-Version: 2.4
Name: AbstractAgents
Version: 0.1.0
Summary: A framework for creating abstract agents using the AbstractLLM unified interface
Author-email: AbstractLLM Team <contact@abstractllm.org>
License: MIT
Project-URL: Homepage, https://github.com/lpalbou/AbstractAgents
Project-URL: Documentation, https://github.com/lpalbou/AbstractAgents/docs
Project-URL: Repository, https://github.com/lpalbou/AbstractAgents
Project-URL: Bug Tracker, https://github.com/lpalbou/AbstractAgents/issues
Project-URL: Changelog, https://github.com/lpalbou/AbstractAgents/blob/main/CHANGELOG.md
Keywords: llm,ai,agents,artificial-intelligence,language-models,openai,anthropic,huggingface
Classifier: Development Status :: 3 - Alpha
Classifier: Intended Audience :: Developers
Classifier: License :: OSI Approved :: MIT License
Classifier: Operating System :: OS Independent
Classifier: Programming Language :: Python :: 3
Classifier: Programming Language :: Python :: 3.8
Classifier: Programming Language :: Python :: 3.9
Classifier: Programming Language :: Python :: 3.10
Classifier: Programming Language :: Python :: 3.11
Classifier: Programming Language :: Python :: 3.12
Classifier: Topic :: Scientific/Engineering :: Artificial Intelligence
Classifier: Topic :: Software Development :: Libraries :: Python Modules
Requires-Python: >=3.8
License-File: LICENSE
Requires-Dist: abstractllm>=0.5.0
Provides-Extra: dev
Requires-Dist: pytest>=7.0.0; extra == "dev"
Requires-Dist: pytest-asyncio>=0.21.0; extra == "dev"
Requires-Dist: black>=23.0.0; extra == "dev"
Requires-Dist: isort>=5.12.0; extra == "dev"
Requires-Dist: flake8>=6.0.0; extra == "dev"
Requires-Dist: mypy>=1.0.0; extra == "dev"
Provides-Extra: all
Requires-Dist: abstractllm[all]; extra == "all"
Dynamic: license-file
